postgres_stats/__init__.py
postgres_stats/aggregates.py
postgres_stats/functions.py
dj_postgres_stats-1.0.3.dev3.dist-info/AUTHORS
dj_postgres_stats-1.0.3.dev3.dist-info/LICENSE
dj_postgres_stats-1.0.3.dev3.dist-info/METADATA
dj_postgres_stats-1.0.3.dev3.dist-info/WHEEL
dj_postgres_stats-1.0.3.dev3.dist-info/pbr.json
dj_postgres_stats-1.0.3.dev3.dist-info/top_level.txt
dj_postgres_stats-1.0.3.dev3.dist-info/RECORD
