Metadata-Version: 2.1
Name: dj-postgres-stats
Version: 1.0.3.dev3
Summary: A Django app to expose built-in statistical and datetime functions from Postgres.
Home-page: https://github.com/ratson/django-postgres-stats/
Author: Clinton Dreisbach
Author-email: cdreisbach@rti.org
License: BSD
Platform: UNKNOWN
Classifier: Development Status :: 4 - Beta
Classifier: Framework :: Django
Classifier: Intended Audience :: Developers
Classifier: License :: OSI Approved :: BSD License
Classifier: Operating System :: OS Independent
Classifier: Programming Language :: Python
Classifier: Programming Language :: Python :: 3
Classifier: Programming Language :: Python :: 3.3
Classifier: Programming Language :: Python :: 3.4
Classifier: Programming Language :: Python :: 3.5
Classifier: Programming Language :: Python :: 3.9
Classifier: Topic :: Database
Requires-Python: >= 3.3
License-File: LICENSE
Requires-Dist: Django (>=1.8.6)
Requires-Dist: psycopg2-binary (>=2.6.1)
Requires-Dist: six (>=1.10.0)
